relevation/PBKDF2.py
relevation/__init__.py
relevation/__main__.py
relevation/gui.py
relevation-1.4rc0.dist-info/METADATA
relevation-1.4rc0.dist-info/WHEEL
relevation-1.4rc0.dist-info/entry_points.txt
relevation-1.4rc0.dist-info/licenses/LICENSE
relevation-1.4rc0.dist-info/RECORD
