Metadata-Version: 2.3
Name: relevation
Version: 1.4rc0
Summary: A command-line searcher for Revelation Password Manager
Project-URL: Homepage, https://p.outlyer.net/relevation
Project-URL: Issues, https://b.outlyer.net/relevation
Project-URL: Documentation, https://p.outlyer.net/relevation
Project-URL: Source, https://git.outlyer.net/outlyer/relevation
Project-URL: Changelog, https://git.outlyer.net/outlyer/relevation/raw/branch/master/CHANGELOG
Author-email: Toni Corvera <outlyer@gmail.com>
License: BSD-2-Clause
License-File: LICENSE
Classifier: Development Status :: 6 - Mature
Classifier: Environment :: Console
Classifier: Operating System :: OS Independent
Classifier: Programming Language :: Python :: 3
Classifier: Programming Language :: Python :: Implementation :: CPython
Classifier: Programming Language :: Python :: Implementation :: PyPy
Requires-Python: >=3.7
Requires-Dist: lxml
Requires-Dist: pycryptodomex
